pyscroll/__init__.py
pyscroll/animation.py
pyscroll/colors.py
pyscroll/common.py
pyscroll/data.py
pyscroll/group.py
pyscroll/isometric.py
pyscroll/orthographic.py
pyscroll/quadtree.py
pyscroll-2.30.dist-info/METADATA
pyscroll-2.30.dist-info/WHEEL
pyscroll-2.30.dist-info/top_level.txt
pyscroll-2.30.dist-info/RECORD
